codingtrackerserver/__init__.py
codingtrackerserver/config.py
codingtrackerserver/persistence.py
codingtrackerserver/process.py
codingtrackerserver/server.py
codingtrackerserver/session.py
codingtrackerserver/sqlhandler.py
codingtrackerserver/tallies.py
codingtrackerserver-0.1.1.dist-info/METADATA
codingtrackerserver-0.1.1.dist-info/WHEEL
codingtrackerserver-0.1.1.dist-info/RECORD
